ffpylon/__init__.py
ffpylon/exec.py
ffpylon/ffmpeg.py
ffpylon/ffmpeg_options.py
ffpylon/ffprobe.py
ffpylon/ffprobe_options.py
ffpylon/meta.py
ffpylon/utils.py
ffpylon-0.3.dist-info/LICENSE
ffpylon-0.3.dist-info/METADATA
ffpylon-0.3.dist-info/WHEEL
ffpylon-0.3.dist-info/top_level.txt
ffpylon-0.3.dist-info/RECORD
