Metadata-Version: 2.1
Name: ffpylon
Version: 0.3
Summary: FFPylon Package
Author: nickdecodes
Author-email: nickdecodes <nickdecodes@163.com>
License: Apache License
Project-URL: Documentation, http://python-ffpylon.readthedocs.io
Project-URL: Source, https://github.com/nickdecodes/python-ffpylon
Keywords: ffpylon,ffmpeg
Requires-Python: >=3.9
License-File: LICENSE
Requires-Dist: twine
Requires-Dist: build
Requires-Dist: installer
